jupyterlab_theme_solarized_dark/__init__.py
jupyterlab_theme_solarized_dark/_version.py
jupyterlab_theme_solarized_dark-3.0.0.data/data/share/jupyter/labextensions/jupyterlab-theme-solarized-dark/package.json
jupyterlab_theme_solarized_dark-3.0.0.data/data/share/jupyter/labextensions/jupyterlab-theme-solarized-dark/static/568.76dc9668e69d5d7e4a81.js
jupyterlab_theme_solarized_dark-3.0.0.data/data/share/jupyter/labextensions/jupyterlab-theme-solarized-dark/static/remoteEntry.4e9357cc5aee17d940f5.js
jupyterlab_theme_solarized_dark-3.0.0.data/data/share/jupyter/labextensions/jupyterlab-theme-solarized-dark/static/style.js
jupyterlab_theme_solarized_dark-3.0.0.data/data/share/jupyter/labextensions/jupyterlab-theme-solarized-dark/static/third-party-licenses.json
jupyterlab_theme_solarized_dark-3.0.0.data/data/share/jupyter/labextensions/jupyterlab-theme-solarized-dark/themes/jupyterlab-theme-solarized-dark/index.css
jupyterlab_theme_solarized_dark-3.0.0.data/data/share/jupyter/labextensions/jupyterlab-theme-solarized-dark/themes/jupyterlab-theme-solarized-dark/index.js
jupyterlab_theme_solarized_dark-3.0.0.data/data/share/jupyter/labextensions/jupyterlab-theme-solarized-dark/install.json
jupyterlab_theme_solarized_dark-3.0.0.dist-info/METADATA
jupyterlab_theme_solarized_dark-3.0.0.dist-info/WHEEL
jupyterlab_theme_solarized_dark-3.0.0.dist-info/licenses/LICENSE
jupyterlab_theme_solarized_dark-3.0.0.dist-info/RECORD
