Metadata-Version: 2.1
Name: jupyterlab_theme_solarized_dark
Version: 3.0.0
Summary: Solarized dark theme for JupyterLab.
Project-URL: Homepage, https://github.com/AllanChain/jupyterlab-theme-solarized-dark
Project-URL: Bug Tracker, https://github.com/AllanChain/jupyterlab-theme-solarized-dark/issues
Project-URL: Repository, https://github.com/AllanChain/jupyterlab-theme-solarized-dark.git
Author-email: Allan Chain <allan-chain@outllok.com>
License: BSD 3-Clause License
License-File: LICENSE
Classifier: Framework :: Jupyter
Classifier: Framework :: Jupyter :: JupyterLab
Classifier: Framework :: Jupyter :: JupyterLab :: 4
Classifier: Framework :: Jupyter :: JupyterLab :: Extensions
Classifier: Framework :: Jupyter :: JupyterLab :: Extensions :: Prebuilt
Classifier: License :: OSI Approved :: BSD License
Classifier: Programming Language :: Python
Classifier: Programming Language :: Python :: 3
Classifier: Programming Language :: Python :: 3.8
Classifier: Programming Language :: Python :: 3.9
Classifier: Programming Language :: Python :: 3.10
Classifier: Programming Language :: Python :: 3.11
Requires-Python: >=3.8
